<mvc:View
    controllerName="nmshd.app.flows.app.About"
    xmlns:m="sap.m"
    xmlns:mvc="sap.ui.core.mvc"
    xmlns:semantic="sap.m.semantic"
    xmlns="sap.uxap"
    xmlns:controls="nmshd.app.core.controls"
>

	<semantic:DetailPage
        id="page"
        navButtonPress="onNavButtonPress"
        showNavButton="{d>/system/phone}"
        title="{t>master.about}"
        showFooter="false"
        busy="{v>/busy}"
        busyIndicatorDelay="{v>/delay}"
    >


		<semantic:customHeaderContent>

		</semantic:customHeaderContent>

		<semantic:content>
            <m:VBox height="100%">
                <m:VBox class="sapUiSmallMargin" visible="{= !${v>/accountCount}}">
                    <m:Title text="{t>about.titleText}" class="bigTitle" wrapping="true" />
                    <m:Text text="{t>about.text1}" class="sapUiTinyMarginBottom" />
                    <m:Text text="{t>about.text2}" class="sapUiTinyMarginBottom" />
                    <m:Text text="{t>about.text3}" class="sapUiTinyMarginBottom" />
                    <m:Button text="{t>about.createProfile}" press="toOnboard()" type="Emphasized" />
                </m:VBox>


                <m:VBox class="sapUiSmallMargin box">
                    <m:Title
                        text="{t>about.what}"
                        class="sapUiSmallMarginTop sapUiSmallMarginBegin sapUiSmallMarginEnd boxTitle"
                    />

                    <m:Carousel
                        id="carousel"
                        height="100%"
                        beforePageChanged="onCarouselPageChange"
                        class="sapUiSmallMargin contentCarousel"
                    >
                    <m:VBox class="sapUiSmallMarginTop">
                        <m:Text text="{t>about.carousel1}" />
                    </m:VBox>
                    <m:VBox class="sapUiSmallMarginTop">
                        <m:Text text="{t>about.carousel2}" />
                    </m:VBox>
                    <m:VBox class="sapUiSmallMarginTop">
                        <m:Text text="{t>about.carousel3}" />
                    </m:VBox>
                    <m:VBox class="sapUiSmallMarginTop">
                        <m:Text text="{t>about.carousel4}" />
                    </m:VBox>
                    <m:VBox class="sapUiSmallMarginTop">
                        <m:Text text="{t>about.carousel5}" />
                    </m:VBox>
                </m:Carousel>

                </m:VBox>


                <m:VBox class="sapUiSmallMargin">
                    <m:Title text="{t>about.moreInfo}" class="contentTitle" />
                    <controls:ContainerButton
                        icon="/assets/icons/info.svg"
                        iconDensityAware="false"
                        press="toAboutProject()"
                        text="{t>about.moreInfoText}"
                    >
                    <controls:contentRight>
                        <m:Image src="/assets/icons/bird.svg" class="big" />
                    </controls:contentRight>
                </controls:ContainerButton>
                </m:VBox>
            </m:VBox>
		</semantic:content>
	</semantic:DetailPage>
</mvc:View>
